{
  "id": "gemeinde-admin",
  "topicId": "practical-swiss-life",
  "title": "At the Gemeinde Office",
  "description": "Registering, deregistering, requesting documents, and dealing with local administration",
  "dialogues": [
    {
      "id": "gemeinde-admin-1",
      "level": "intermediate",
      "title": "Registering at the commune (Anmeldung)",
      "situation": "You've just moved to a new town and need to register at the Gemeinde.",
      "lines": [
        {
          "speaker": "You",
          "swissGerman": "Grüezi! Ich bi nöi i de Gmeind und möcht mich aalüte... äh, aamälde.",
          "german": "Grüezi! Ich bin neu in der Gemeinde und möchte mich anmelden.",
          "english": "Hello! I'm new in the municipality and would like to register.",
          "spanish": "¡Hola! Soy nuevo en el municipio y me gustaría empadronarme."
        },
        {
          "speaker": "Officer",
          "swissGerman": "Grüezi! Händ Si scho e Wohnig gfunde?",
          "german": "Grüezi! Haben Sie schon eine Wohnung gefunden?",
          "english": "Hello! Have you already found an apartment?",
          "spanish": "¡Hola! ¿Ya ha encontrado apartamento?"
        },
        {
          "speaker": "You",
          "swissGerman": "Ja, ich bi am Erschte April iizoge.",
          "german": "Ja, ich bin am ersten April eingezogen.",
          "english": "Yes, I moved in on April first.",
          "spanish": "Sí, me mudé el uno de abril."
        },
        {
          "speaker": "Officer",
          "swissGerman": "Guet. Ich bruuch Ihre Uuswiis oder Pass, de Mietvertrag und e Bestätigig vo de alte Gmeind.",
          "german": "Gut. Ich brauche Ihren Ausweis oder Pass, den Mietvertrag und eine Bestätigung von der alten Gemeinde.",
          "english": "Good. I need your ID or passport, the rental contract, and a confirmation from the old municipality.",
          "spanish": "Bien. Necesito su DNI o pasaporte, el contrato de alquiler y una confirmación del antiguo municipio."
        },
        {
          "speaker": "You",
          "swissGerman": "Do isch alles. Ich ha au d'Abmäldig vo minere alte Gmeind.",
          "german": "Hier ist alles. Ich habe auch die Abmeldung von meiner alten Gemeinde.",
          "english": "Here's everything. I also have the deregistration from my old municipality.",
          "spanish": "Aquí está todo. También tengo la baja del antiguo municipio."
        },
        {
          "speaker": "Officer",
          "swissGerman": "Super. Sind Si allei oder zieht no öpper mit Ine ii?",
          "german": "Super. Sind Sie allein oder zieht noch jemand mit Ihnen ein?",
          "english": "Great. Are you alone or is someone else moving in with you?",
          "spanish": "Genial. ¿Estás solo o se muda alguien más contigo?"
        },
        {
          "speaker": "You",
          "swissGerman": "Min Partnerin chunt im Mai noche.",
          "german": "Meine Partnerin kommt im Mai nach.",
          "english": "My partner will follow in May.",
          "spanish": "Mi pareja vendrá en mayo."
        },
        {
          "speaker": "Officer",
          "swissGerman": "Denn muess si sich au aamälde, innerhalb vo vierzäh Tääg nach em Iizug.",
          "german": "Dann muss sie sich auch anmelden, innerhalb von vierzehn Tagen nach dem Einzug.",
          "english": "Then she needs to register too, within fourteen days of moving in.",
          "spanish": "Entonces ella también tiene que registrarse, dentro de los catorce días de mudarse."
        },
        {
          "speaker": "You",
          "swissGerman": "Verstande. Und was choschtet d'Aamäldig?",
          "german": "Verstanden. Und was kostet die Anmeldung?",
          "english": "Understood. And what does the registration cost?",
          "spanish": "Entendido. ¿Y cuánto cuesta el registro?"
        },
        {
          "speaker": "Officer",
          "swissGerman": "Zwänzg Franke pro Person.",
          "german": "Zwanzig Franken pro Person.",
          "english": "Twenty francs per person.",
          "spanish": "Veinte francos por persona."
        }
      ],
      "differences": [
        {
          "swissGerman": "Gmeind",
          "german": "Gemeinde",
          "explanation": "'Gmeind' = 'Gemeinde'. Contracted form."
        },
        {
          "swissGerman": "aamälde",
          "german": "anmelden",
          "explanation": "'aamälde' = 'anmelden'. 'an' → 'aa', 'e' → 'ä'."
        },
        {
          "swissGerman": "Abmäldig",
          "german": "Abmeldung",
          "explanation": "'Abmäldig' = 'Abmeldung'. '-ung' → '-ig'."
        },
        {
          "swissGerman": "iizoge",
          "german": "eingezogen",
          "explanation": "'iizoge' = 'eingezogen'. 'ein' → 'ii', no 'ge-'."
        },
        {
          "swissGerman": "noche",
          "german": "nach",
          "explanation": "'noche' = 'nach/nachkommen'. To follow."
        }
      ],
      "keyPhrases": [
        {
          "swissGerman": "aamälde",
          "german": "anmelden",
          "english": "to register"
        },
        {
          "swissGerman": "Abmäldig",
          "german": "Abmeldung",
          "english": "deregistration"
        },
        {
          "swissGerman": "Iizug",
          "german": "Einzug",
          "english": "move-in"
        }
      ]
    },
    {
      "id": "gemeinde-admin-2",
      "level": "intermediate",
      "title": "Deregistering before moving away",
      "situation": "You're leaving the municipality and need to deregister.",
      "lines": [
        {
          "speaker": "You",
          "swissGerman": "Grüezi! Ich zügle am Ändi vom Monet und möcht mich abmälde.",
          "german": "Grüezi! Ich ziehe am Ende des Monats um und möchte mich abmelden.",
          "english": "Hello! I'm moving at the end of the month and would like to deregister.",
          "spanish": "¡Hola! Me mudo a final de mes y me gustaría darme de baja."
        },
        {
          "speaker": "Officer",
          "swissGerman": "Wohi zügled Si?",
          "german": "Wohin ziehen Sie?",
          "english": "Where are you moving to?",
          "spanish": "¿Adónde te mudas?"
        },
        {
          "speaker": "You",
          "swissGerman": "Uf Bärn. Ich ha deet scho e Wohnig.",
          "german": "Nach Bern. Ich habe dort schon eine Wohnung.",
          "english": "To Bern. I already have an apartment there.",
          "spanish": "A Berna. Ya tengo un apartamento allí."
        },
        {
          "speaker": "Officer",
          "swissGerman": "Guet. Händ Si no offnigi Rechnige bi de Gmeind?",
          "german": "Gut. Haben Sie noch offene Rechnungen bei der Gemeinde?",
          "english": "Good. Do you have any open bills with the municipality?",
          "spanish": "Bien. ¿Tiene alguna factura pendiente con el municipio?"
        },
        {
          "speaker": "You",
          "swissGerman": "Nei, ich ha alles zahlt.",
          "german": "Nein, ich habe alles bezahlt.",
          "english": "No, I've paid everything.",
          "spanish": "No, ya lo he pagado todo."
        },
        {
          "speaker": "Officer",
          "swissGerman": "Perfekt. Si überchömed denn e Abmäldebestätigig per Post a d'nöii Adrässe.",
          "german": "Perfekt. Sie bekommen dann eine Abmeldebestätigung per Post an die neue Adresse.",
          "english": "Perfect. You'll receive a deregistration confirmation by mail to the new address.",
          "spanish": "Perfecto. Recibirás una confirmación de baja por correo a la nueva dirección."
        },
        {
          "speaker": "You",
          "swissGerman": "Und muess ich d'Stüüre no da zahle?",
          "german": "Und muss ich die Steuern noch hier zahlen?",
          "english": "And do I still need to pay taxes here?",
          "spanish": "¿Y todavía tengo que pagar impuestos aquí?"
        },
        {
          "speaker": "Officer",
          "swissGerman": "Ja, für s'laufende Jahr bis zum Umzugsdatum. De Räscht zahled Si denn i Bärn.",
          "german": "Ja, für das laufende Jahr bis zum Umzugsdatum. Den Rest zahlen Sie dann in Bern.",
          "english": "Yes, for the current year until the moving date. The rest you'll pay in Bern.",
          "spanish": "Sí, para el año en curso hasta la fecha de mudanza. El resto lo pagarás en Berna."
        }
      ],
      "differences": [
        {
          "swissGerman": "zügle",
          "german": "umziehen",
          "explanation": "'zügle' = 'umziehen'. Swiss word for moving house."
        },
        {
          "swissGerman": "Wohi",
          "german": "Wohin",
          "explanation": "'Wohi' = 'Wohin'. Shortened form."
        },
        {
          "swissGerman": "offnigi",
          "german": "offene",
          "explanation": "'offnigi' = 'offene'. Swiss adjective form."
        },
        {
          "swissGerman": "Stüüre",
          "german": "Steuern",
          "explanation": "'Stüüre' = 'Steuern'. Swiss vowel shift."
        },
        {
          "swissGerman": "Adrässe",
          "german": "Adresse",
          "explanation": "'Adrässe' = 'Adresse'. 'e' → 'ä'."
        }
      ],
      "keyPhrases": [
        {
          "swissGerman": "abmälde",
          "german": "abmelden",
          "english": "to deregister"
        },
        {
          "swissGerman": "zügle",
          "german": "umziehen",
          "english": "to move (house)"
        },
        {
          "swissGerman": "Stüüre",
          "german": "Steuern",
          "english": "taxes"
        }
      ]
    },
    {
      "id": "gemeinde-admin-3",
      "level": "beginner",
      "title": "Requesting an official document",
      "situation": "You need a Wohnsitzbestätigung (proof of residence) for your employer.",
      "lines": [
        {
          "speaker": "You",
          "swissGerman": "Grüezi! Ich bruuch e Wohnsitzbestätigig für min Arbeitgäber.",
          "german": "Grüezi! Ich brauche eine Wohnsitzbestätigung für meinen Arbeitgeber.",
          "english": "Hello! I need a proof of residence for my employer.",
          "spanish": "¡Hola! Necesito un certificado de empadronamiento para mi empleador."
        },
        {
          "speaker": "Officer",
          "swissGerman": "Händ Si Ihre Uuswiis debii?",
          "german": "Haben Sie Ihren Ausweis dabei?",
          "english": "Do you have your ID with you?",
          "spanish": "¿Tienes el DNI contigo?"
        },
        {
          "speaker": "You",
          "swissGerman": "Ja, do bitte.",
          "german": "Ja, hier bitte.",
          "english": "Yes, here please.",
          "spanish": "Sí, aquí por favor."
        },
        {
          "speaker": "Officer",
          "swissGerman": "Merci. Möchted Si's grad mitnä, oder söll ich's per Post schicke?",
          "german": "Danke. Möchten Sie es gleich mitnehmen, oder soll ich es per Post schicken?",
          "english": "Thanks. Would you like to take it right away, or should I send it by mail?",
          "spanish": "Gracias. ¿Lo quieres llevar ahora o lo mando por correo?"
        },
        {
          "speaker": "You",
          "swissGerman": "Grad mitnä, wenn's goht.",
          "german": "Gleich mitnehmen, wenn es geht.",
          "english": "Take it right away, if possible.",
          "spanish": "Cógetelo ahora mismo, si es posible."
        },
        {
          "speaker": "Officer",
          "swissGerman": "Klar, das isch i öppe fünf Minute parat. Das choschtet zwänzg Franke.",
          "german": "Klar, das ist in ungefähr fünf Minuten fertig. Das kostet zwanzig Franken.",
          "english": "Sure, that'll be ready in about five minutes. That costs twenty francs.",
          "spanish": "Claro, eso estará listo en unos cinco minutos. Cuesta veinte francos."
        },
        {
          "speaker": "You",
          "swissGerman": "Perfekt, merci!",
          "german": "Perfekt, danke!",
          "english": "Perfect, thanks!",
          "spanish": "¡Perfecto, gracias!"
        }
      ],
      "differences": [
        {
          "swissGerman": "Wohnsitzbestätigig",
          "german": "Wohnsitzbestätigung",
          "explanation": "'-ung' → '-ig'. Standard Swiss suffix change."
        },
        {
          "swissGerman": "Uuswiis",
          "german": "Ausweis",
          "explanation": "'Uuswiis' = 'Ausweis'. 'Au' → 'Uu', 'ei' → 'ii'."
        },
        {
          "swissGerman": "grad mitnä",
          "german": "gleich mitnehmen",
          "explanation": "'grad' = 'gleich', 'mitnä' = 'mitnehmen'."
        },
        {
          "swissGerman": "parat",
          "german": "fertig/bereit",
          "explanation": "'parat' = 'fertig'. Swiss word from French 'paré'."
        }
      ],
      "keyPhrases": [
        {
          "swissGerman": "Wohnsitzbestätigig",
          "german": "Wohnsitzbestätigung",
          "english": "proof of residence"
        },
        {
          "swissGerman": "Uuswiis",
          "german": "Ausweis",
          "english": "ID card"
        },
        {
          "swissGerman": "parat",
          "german": "fertig/bereit",
          "english": "ready"
        }
      ]
    },
    {
      "id": "gemeinde-admin-4",
      "level": "intermediate",
      "title": "Understanding a letter from the Gemeinde",
      "situation": "You received an official letter from the municipality and go to the office to ask about it.",
      "lines": [
        {
          "speaker": "You",
          "swissGerman": "Grüezi! Ich ha en Brief vo de Gmeind übercho und verstah nöd, was ich muess mache.",
          "german": "Grüezi! Ich habe einen Brief von der Gemeinde bekommen und verstehe nicht, was ich tun muss.",
          "english": "Hello! I received a letter from the municipality and don't understand what I need to do.",
          "spanish": "¡Hola! Recibí una carta del municipio y no entiendo qué tengo que hacer."
        },
        {
          "speaker": "Officer",
          "swissGerman": "Zeiiged Si mir de Brief bitte.",
          "german": "Zeigen Sie mir den Brief bitte.",
          "english": "Please show me the letter.",
          "spanish": "Por favor, muéstrame la carta."
        },
        {
          "speaker": "You",
          "swissGerman": "Do, bitte. Da stoht öppis vo ere 'Verfüegig'.",
          "german": "Hier, bitte. Da steht etwas von einer 'Verfügung'.",
          "english": "Here, please. It says something about a 'Verfügung' (official order).",
          "spanish": "Aquí, por favor. Dice algo sobre una 'Verfügung' (resolución oficial)."
        },
        {
          "speaker": "Officer",
          "swissGerman": "Ah ja, das isch e Verfüegig beträffend Ihri Hundesteuer. Si müend die no zahle.",
          "german": "Ah ja, das ist eine Verfügung betreffend Ihre Hundesteuer. Sie müssen die noch zahlen.",
          "english": "Ah yes, that's an official order regarding your dog tax. You still need to pay it.",
          "spanish": "Ah, sí, es una orden oficial sobre el impuesto de tu perro. Todavía necesitas pagarlo."
        },
        {
          "speaker": "You",
          "swissGerman": "Hoppla! Ich ha nöd gwüsst, dass ich das muess zahle. Bis wänn isch d'Frischt?",
          "german": "Hoppla! Ich wusste nicht, dass ich das bezahlen muss. Bis wann ist die Frist?",
          "english": "Oops! I didn't know I had to pay that. When is the deadline?",
          "spanish": "¡Ups! No sabía que tenía que pagar eso. ¿Cuándo es el plazo?"
        },
        {
          "speaker": "Officer",
          "swissGerman": "Bis zum Ändi vom Monet. Susch chunt en Mahnig.",
          "german": "Bis zum Ende des Monats. Sonst kommt eine Mahnung.",
          "english": "By the end of the month. Otherwise you'll get a reminder.",
          "spanish": "Antes de que acabe el mes. De lo contrario recibirás un recordatorio."
        },
        {
          "speaker": "You",
          "swissGerman": "Cha ich das grad do zahle?",
          "german": "Kann ich das gleich hier bezahlen?",
          "english": "Can I pay it right here?",
          "spanish": "¿Puedo pagarlo aquí mismo?"
        },
        {
          "speaker": "Officer",
          "swissGerman": "Ja, mit Charte oder bar. Hundertfüfzäh Franke bitte.",
          "german": "Ja, mit Karte oder bar. Hundertfünfzehn Franken bitte.",
          "english": "Yes, by card or cash. One hundred fifteen francs please.",
          "spanish": "Sí, con tarjeta o en efectivo. Ciento quince francos, por favor."
        }
      ],
      "differences": [
        {
          "swissGerman": "Verfüegig",
          "german": "Verfügung",
          "explanation": "'Verfüegig' = 'Verfügung'. Official order/decree, '-ung' → '-ig'."
        },
        {
          "swissGerman": "beträffend",
          "german": "betreffend",
          "explanation": "'beträffend' = 'betreffend'. 'e' → 'ä' shift."
        },
        {
          "swissGerman": "Frischt",
          "german": "Frist",
          "explanation": "'Frischt' = 'Frist'. Added 'ch'."
        },
        {
          "swissGerman": "Mahnig",
          "german": "Mahnung",
          "explanation": "'Mahnig' = 'Mahnung'. '-ung' → '-ig'."
        }
      ],
      "keyPhrases": [
        {
          "swissGerman": "Verfüegig",
          "german": "Verfügung",
          "english": "official order / decree"
        },
        {
          "swissGerman": "Frischt",
          "german": "Frist",
          "english": "deadline"
        },
        {
          "swissGerman": "Mahnig",
          "german": "Mahnung",
          "english": "reminder / warning notice"
        }
      ]
    },
    {
      "id": "gemeinde-admin-5",
      "level": "beginner",
      "title": "Basic interaction at the counter",
      "situation": "You arrive at the Gemeinde counter without an appointment for a quick question.",
      "lines": [
        {
          "speaker": "You",
          "swissGerman": "Grüezi! Ich ha kein Termin, aber ich ha nur e churzi Frog.",
          "german": "Grüezi! Ich habe keinen Termin, aber ich habe nur eine kurze Frage.",
          "english": "Hello! I don't have an appointment, but I just have a quick question.",
          "spanish": "¡Hola! No tengo cita, pero solo tengo una pregunta rápida."
        },
        {
          "speaker": "Officer",
          "swissGerman": "Grüezi! Ja, säged Si.",
          "german": "Grüezi! Ja, sagen Sie.",
          "english": "Hello! Yes, go ahead.",
          "spanish": "¡Hola! Sí, adelante."
        },
        {
          "speaker": "You",
          "swissGerman": "Wo chan ich en Betriibigsuuszug becho?",
          "german": "Wo kann ich einen Betreibungsauszug bekommen?",
          "english": "Where can I get a debt enforcement extract?",
          "spanish": "¿Dónde puedo obtener un extracto de ejecución de deudas?"
        },
        {
          "speaker": "Officer",
          "swissGerman": "Das isch nöd bi üs. Sie müend zum Betriibungsamt. Das isch im dritte Stock.",
          "german": "Das ist nicht bei uns. Sie müssen zum Betreibungsamt. Das ist im dritten Stock.",
          "english": "That's not with us. You need to go to the debt enforcement office. It's on the third floor.",
          "spanish": "Eso no es con nosotros. Tienes que ir a la oficina de ejecución de deudas. Está en el tercer piso."
        },
        {
          "speaker": "You",
          "swissGerman": "Ah, im dritte Stock. Bruuch ich en Termin derfür?",
          "german": "Ah, im dritten Stock. Brauche ich einen Termin dafür?",
          "english": "Ah, third floor. Do I need an appointment for that?",
          "spanish": "Ah, tercer piso. ¿Necesito cita para eso?"
        },
        {
          "speaker": "Officer",
          "swissGerman": "Nei, die händ offnigi Schalteröffnigsziite. Am Morge vo achti bis halbi zwölfi.",
          "german": "Nein, die haben offene Schalteröffnungszeiten. Morgens von acht bis halb zwölf.",
          "english": "No, they have open counter hours. Mornings from eight to eleven-thirty.",
          "spanish": "No, tienen horario de atención presencial. Por las mañanas de ocho a once y media."
        },
        {
          "speaker": "You",
          "swissGerman": "Super, dankeschön!",
          "german": "Super, dankeschön!",
          "english": "Great, thank you!",
          "spanish": "¡Genial, gracias!"
        }
      ],
      "differences": [
        {
          "swissGerman": "Betriibigsuuszug",
          "german": "Betreibungsauszug",
          "explanation": "'Betriibigs-' = 'Betreibungs-', 'uuszug' = 'Auszug'. Debt enforcement extract — essential Swiss document."
        },
        {
          "swissGerman": "Betriibungsamt",
          "german": "Betreibungsamt",
          "explanation": "'Betriibungsamt' = 'Betreibungsamt'. Debt enforcement office."
        },
        {
          "swissGerman": "Schalteröffnigsziite",
          "german": "Schalteröffnungszeiten",
          "explanation": "Swiss compound: 'Schalter' (counter) + 'öffnig' (opening) + 'ziite' (times)."
        }
      ],
      "keyPhrases": [
        {
          "swissGerman": "Betriibigsuuszug",
          "german": "Betreibungsauszug",
          "english": "debt enforcement extract"
        },
        {
          "swissGerman": "Schalteröffnigsziite",
          "german": "Schalteröffnungszeiten",
          "english": "counter opening hours"
        },
        {
          "swissGerman": "churzi Frog",
          "german": "kurze Frage",
          "english": "quick question"
        }
      ]
    }
  ]
}